setech/__init__.py
setech/py.typed
setech/api_client/__init__.py
setech/api_client/_base.py
setech/api_client/async_client.py
setech/api_client/sync_client.py
setech/api_client/utils.py
setech/constants/__init__.py
setech/constants/date.py
setech/constants/status_code.py
setech/constants/types.py
setech/logging/__init__.py
setech/logging/formatters.py
setech/logging/handlers.py
setech/utils/__init__.py
setech/utils/numeric.py
setech/utils/parse.py
setech/utils/ssn.py
setech/utils/text.py
setech/utils/time.py
setech/utils/validators.py
setech/utils/various.py
setech/utils/warnings.py
setech-1.5.4.dist-info/licenses/LICENCE
setech-1.5.4.dist-info/METADATA
setech-1.5.4.dist-info/WHEEL
setech-1.5.4.dist-info/top_level.txt
setech-1.5.4.dist-info/RECORD
