Metadata-Version: 2.4
Name: setech
Version: 1.5.4
Summary: Setech utilities
Author-email: Eriks Karls <eriks.karls@sefinance.lv>
Project-URL: Homepage, https://pypi.org/project/setech/
Keywords: setech,logging,api-client,utility,utils
Classifier: Development Status :: 5 - Production/Stable
Classifier: Intended Audience :: Developers
Classifier: Programming Language :: Python :: 3
Classifier: Programming Language :: Python :: 3.10
Classifier: Programming Language :: Python :: 3.11
Classifier: Programming Language :: Python :: 3.12
Classifier: Programming Language :: Python :: 3 :: Only
Classifier: License :: OSI Approved :: MIT License
Classifier: Operating System :: OS Independent
Requires-Python: ~=3.11
License-File: LICENCE
Requires-Dist: httpx[http2]~=0.28
Requires-Dist: pydantic~=2.12
Requires-Dist: num2words==0.5.14
Requires-Dist: unidecode~=1.4
Dynamic: license-file
